// converted by version 1.3
// on Mon Dec 01 14:36:54 CST 2008

.package net/sourceforge/openjcvm/test/ShortInstanceOf {
	.aid 0xA0:0x0:0x0:0x0:0x0:0x0:0x0:0xE;
	.version 1.0;

	.imports {
		0xA0:0x0:0x0:0x0:0x62:0x0:0x1 1.0;		//java/lang
		0xA0:0x0:0x0:0x0:0x62:0x1:0x1 1.2;		//javacard/framework
	}

	.applet {
		0xA0:0x0:0x0:0x0:0x0:0x0:0x0:0xE:0x1 ShortInstanceOf;
	}

	.constantPool {
		// 0
		staticMethodRef 0.0.0()V;		// java/lang/Object.<init>()V
		// 1
		staticMethodRef ClassLevel1/<init>()V;
		// 2
		staticMethodRef ClassLevel2/<init>()V;
		// 3
		staticMethodRef ClassLevel3/<init>()V;
		// 4
		classRef 0.0;		// java/lang/Object
		// 5
		classRef ClassLevel1;
		// 6
		classRef ClassLevel2;
		// 7
		classRef ClassLevel3;
		// 8
		classRef ClassLevel4;
		// 9
		staticMethodRef ClassLevel4/<init>()V;
		// 10
		classRef InterfaceLevel1;
		// 11
		classRef Class2;
		// 12
		staticMethodRef 1.3.0()V;		// javacard/framework/Applet.<init>()V
	}

	.interface public abstract InterfaceLevel1 0 {

	}

	.class public ClassLevel1 1 extends 0.0 {		// extends java/lang/Object

		.publicMethodTable 1 {
			equals(Ljava/lang/Object;)Z;
		}

		.packageMethodTable 0 {
		}

		.implementedInterfaceInfoTable { 
			.interface InterfaceLevel1 { 
			}

		}

		.method public <init>()V 0 {
			.stack 1;
			.locals 0;

				L0:	aload_0;
					invokespecial 0;		// java/lang/Object.<init>()V
					return;
		}

	}

	.class public ClassLevel2 2 extends ClassLevel1 {

		.publicMethodTable 1 {
			equals(Ljava/lang/Object;)Z;
		}

		.packageMethodTable 0 {
		}

		.implementedInterfaceInfoTable { 
			.interface InterfaceLevel1 { 
			}

		}

		.method public <init>()V 0 {
			.stack 1;
			.locals 0;

				L0:	aload_0;
					invokespecial 1;		// net/sourceforge/openjcvm/test/ShortInstanceOf/ClassLevel1.<init>()V
					return;
		}

	}

	.class public ClassLevel3 3 extends ClassLevel2 {

		.publicMethodTable 1 {
			equals(Ljava/lang/Object;)Z;
		}

		.packageMethodTable 0 {
		}

		.implementedInterfaceInfoTable { 
			.interface InterfaceLevel1 { 
			}

		}

		.method public <init>()V 0 {
			.stack 1;
			.locals 0;

				L0:	aload_0;
					invokespecial 2;		// net/sourceforge/openjcvm/test/ShortInstanceOf/ClassLevel2.<init>()V
					return;
		}

	}

	.class public ClassLevel4 4 extends ClassLevel3 {

		.publicMethodTable 1 {
			equals(Ljava/lang/Object;)Z;
		}

		.packageMethodTable 0 {
		}

		.implementedInterfaceInfoTable { 
			.interface InterfaceLevel1 { 
			}

		}

		.method public <init>()V 0 {
			.stack 1;
			.locals 0;

				L0:	aload_0;
					invokespecial 3;		// net/sourceforge/openjcvm/test/ShortInstanceOf/ClassLevel3.<init>()V
					return;
		}

	}

	.class public Class2 5 extends 0.0 {		// extends java/lang/Object

		.publicMethodTable 1 {
			equals(Ljava/lang/Object;)Z;
		}

		.packageMethodTable 0 {
		}

		.method public <init>()V 0 {
			.stack 1;
			.locals 0;

				L0:	aload_0;
					invokespecial 0;		// java/lang/Object.<init>()V
					return;
		}

	}

	.class public ShortInstanceOf 6 extends 1.3 {		// extends javacard/framework/Applet

		.fields {
			public static final short ELEM_NUM = 9;		// S
		}

		.publicMethodTable 7 {
			equals(Ljava/lang/Object;)Z;
			register()V;
			register([BSB)V;
			selectingApplet()Z;
			deselect()V;
			getShareableInterfaceObject(Ljavacard/framework/AID;B)Ljavacard/framework/Shareable;;
			select()Z;
			process(Ljavacard/framework/APDU;)V;
		}

		.packageMethodTable 0 {
		}

		.method public static install([BSB)V 0 {
			.stack 4;
			.locals 6;

				L0:	bspush 9;
					anewarray 4;		// java/lang/Object
					astore_3;
					aload_3;
					sconst_0;
					bspush 10;
					newarray 12;
					aastore;
					aload_3;
					sconst_1;
					bspush 10;
					newarray 10;
					aastore;
					aload_3;
					sconst_2;
					bspush 10;
					newarray 11;
					aastore;
					aload_3;
					sconst_3;
					new 4;		// java/lang/Object
					dup;
					invokespecial 0;		// java/lang/Object.<init>()V
					aastore;
					aload_3;
					sconst_4;
					new 5;		// net/sourceforge/openjcvm/test/ShortInstanceOf/ClassLevel1
					dup;
					invokespecial 1;		// net/sourceforge/openjcvm/test/ShortInstanceOf/ClassLevel1.<init>()V
					aastore;
					aload_3;
					sconst_5;
					new 6;		// net/sourceforge/openjcvm/test/ShortInstanceOf/ClassLevel2
					dup;
					invokespecial 2;		// net/sourceforge/openjcvm/test/ShortInstanceOf/ClassLevel2.<init>()V
					aastore;
					aload_3;
					bspush 6;
					new 7;		// net/sourceforge/openjcvm/test/ShortInstanceOf/ClassLevel3
					dup;
					invokespecial 3;		// net/sourceforge/openjcvm/test/ShortInstanceOf/ClassLevel3.<init>()V
					aastore;
					aload_3;
					bspush 7;
					new 8;		// net/sourceforge/openjcvm/test/ShortInstanceOf/ClassLevel4
					dup;
					invokespecial 9;		// net/sourceforge/openjcvm/test/ShortInstanceOf/ClassLevel4.<init>()V
					aastore;
					aload_3;
					bspush 8;
					aconst_null;
					aastore;
					bspush 9;
					newarray 10;
					astore 4;
					bspush 9;
					newarray 10;
					astore 5;
					bspush 9;
					newarray 10;
					astore 6;
					bspush 9;
					newarray 10;
					astore 7;
					sconst_0;
					sstore 8;
					goto L2;
				L1:	aload 4;
					sload 8;
					aload_3;
					sload 8;
					aaload;
					instanceof 0 4;		// T_CLASSORINTERFACE java/lang/Object
					bastore;
					aload 5;
					sload 8;
					aload_3;
					sload 8;
					aaload;
					instanceof 0 5;		// T_CLASSORINTERFACE net/sourceforge/openjcvm/test/ShortInstanceOf/ClassLevel1
					bastore;
					aload 6;
					sload 8;
					aload_3;
					sload 8;
					aaload;
					instanceof 0 10;		// T_CLASSORINTERFACE net/sourceforge/openjcvm/test/ShortInstanceOf/InterfaceLevel1
					bastore;
					aload 7;
					sload 8;
					aload_3;
					sload 8;
					aaload;
					instanceof 0 11;		// T_CLASSORINTERFACE net/sourceforge/openjcvm/test/ShortInstanceOf/Class2
					bastore;
					sinc 8 1;
				L2:	sload 8;
					aload_3;
					arraylength;
					if_scmplt L1;
				L3:	return;
		}

		.method public <init>()V 1 {
			.stack 1;
			.locals 0;

				L0:	aload_0;
					invokespecial 12;		// javacard/framework/Applet.<init>()V
					return;
		}

		.method public process(Ljavacard/framework/APDU;)V 7 {
			.stack 0;
			.locals 0;

			.descriptor	Ljavacard/framework/APDU;	1.10;

				L0:	return;
		}

	}

}
